YT_Sentiments/__init__.py
YT_Sentiments/sentiment.py
YT_Sentiments/test_analyze.py
YT_Sentiments/helpers/__init__.py
YT_Sentiments/helpers/sentimentScore.py
YT_Sentiments/helpers/ytComments.py
YT_Sentiments-0.0.6.dist-info/LICENSE
YT_Sentiments-0.0.6.dist-info/METADATA
YT_Sentiments-0.0.6.dist-info/WHEEL
YT_Sentiments-0.0.6.dist-info/top_level.txt
YT_Sentiments-0.0.6.dist-info/RECORD
