Metadata-Version: 2.1
Name: YT-Sentiments
Version: 0.0.6
Summary: analyze up to 12000 comments from any youtube video!
Home-page: https://github.com/ZhengJiawen44/YT_Sentiment_Analyzer
Author: Zheng Jiawen
Author-email: zhengjiawen44@gmail.com
License: MIT
Classifier: Development Status :: 5 - Production/Stable
Classifier: Programming Language :: Python
Classifier: Topic :: Software Development :: Libraries :: Python Modules
Classifier: Operating System :: OS Independent
Requires-Python: >=3.10
License-File: LICENSE
Requires-Dist: emoji (>=2.12.1)
Requires-Dist: google-api-python-client (>=2.139.0)
Requires-Dist: vaderSentiment (>=3.3.2)
